main.py
aws_delete_all-0.5.52.dist-info/LICENSE
aws_delete_all-0.5.52.dist-info/METADATA
aws_delete_all-0.5.52.dist-info/WHEEL
aws_delete_all-0.5.52.dist-info/entry_points.txt
aws_delete_all-0.5.52.dist-info/top_level.txt
aws_delete_all-0.5.52.dist-info/RECORD
