Metadata-Version: 2.1
Name: aws-delete-all
Version: 0.5.52
Summary: A script that concurrently deletes common AWS resources like S3 buckets, RDS instances, and EC2 instances across all AWS regions.
Home-page: https://github.com/sinanartun/aws_delete_all
Author: Sinan Artun
Author-email: sinanartun@gmail.com
Classifier: Programming Language :: Python :: 3
Classifier: License :: OSI Approved :: MIT License
Classifier: Operating System :: OS Independent
Requires-Python: >=3.9
License-File: LICENSE
Requires-Dist: boto3>=1.35.74
Requires-Dist: loguru
Requires-Dist: pip>=24.1.1
